SecondOrderCoefficient/__init__.py
SecondOrderCoefficient/second_order_average_degree.py
SecondOrderCoefficient/second_order_max_degree.py
SecondOrderCoefficient-1.0.4.dev1.dist-info/DESCRIPTION.rst
SecondOrderCoefficient-1.0.4.dev1.dist-info/METADATA
SecondOrderCoefficient-1.0.4.dev1.dist-info/RECORD
SecondOrderCoefficient-1.0.4.dev1.dist-info/WHEEL
SecondOrderCoefficient-1.0.4.dev1.dist-info/metadata.json
SecondOrderCoefficient-1.0.4.dev1.dist-info/top_level.txt
