Metadata-Version: 2.0
Name: SecondOrderCoefficient
Version: 1.0.4.dev1
Summary: Calculate the Second Order Coefficient of a complex network
Home-page: https://github.com/HaoruoLiu/SecondOrderCoefficient
Author: Haoruo Liu
Author-email: haoruo.liu@qq.com
License: UNKNOWN
Platform: UNKNOWN
